
{"items":[{"name":"Bonsai.ML","href":"Bonsai.ML.html","topicHref":"Bonsai.ML.html","topicUid":"Bonsai.ML","items":[{"name":"CreateModelReference","href":"Bonsai.ML.CreateModelReference.html","topicHref":"Bonsai.ML.CreateModelReference.html","topicUid":"Bonsai.ML.CreateModelReference"},{"name":"ModelReference","href":"Bonsai.ML.ModelReference.html","topicHref":"Bonsai.ML.ModelReference.html","topicUid":"Bonsai.ML.ModelReference"},{"name":"NumpyHelper","href":"Bonsai.ML.NumpyHelper.html","topicHref":"Bonsai.ML.NumpyHelper.html","topicUid":"Bonsai.ML.NumpyHelper"},{"name":"NumpyHelper.NumpyArrayInterface","href":"Bonsai.ML.NumpyHelper.NumpyArrayInterface.html","topicHref":"Bonsai.ML.NumpyHelper.NumpyArrayInterface.html","topicUid":"Bonsai.ML.NumpyHelper.NumpyArrayInterface"},{"name":"NumpyHelper.NumpyDataTypes","href":"Bonsai.ML.NumpyHelper.NumpyDataTypes.html","topicHref":"Bonsai.ML.NumpyHelper.NumpyDataTypes.html","topicUid":"Bonsai.ML.NumpyHelper.NumpyDataTypes"},{"name":"NumpyHelper.NumpyParser","href":"Bonsai.ML.NumpyHelper.NumpyParser.html","topicHref":"Bonsai.ML.NumpyHelper.NumpyParser.html","topicUid":"Bonsai.ML.NumpyHelper.NumpyParser"},{"name":"PythonHelper","href":"Bonsai.ML.PythonHelper.html","topicHref":"Bonsai.ML.PythonHelper.html","topicUid":"Bonsai.ML.PythonHelper"}]},{"name":"Bonsai.ML.HiddenMarkovModels","href":"Bonsai.ML.HiddenMarkovModels.html","topicHref":"Bonsai.ML.HiddenMarkovModels.html","topicUid":"Bonsai.ML.HiddenMarkovModels","items":[{"name":"DeserializeFromJson","href":"Bonsai.ML.HiddenMarkovModels.DeserializeFromJson.html","topicHref":"Bonsai.ML.HiddenMarkovModels.DeserializeFromJson.html","topicUid":"Bonsai.ML.HiddenMarkovModels.DeserializeFromJson"},{"name":"FormatToPythonList","href":"Bonsai.ML.HiddenMarkovModels.FormatToPythonList.html","topicHref":"Bonsai.ML.HiddenMarkovModels.FormatToPythonList.html","topicUid":"Bonsai.ML.HiddenMarkovModels.FormatToPythonList"},{"name":"ModelParameters","href":"Bonsai.ML.HiddenMarkovModels.ModelParameters.html","topicHref":"Bonsai.ML.HiddenMarkovModels.ModelParameters.html","topicUid":"Bonsai.ML.HiddenMarkovModels.ModelParameters"},{"name":"ModelParametersJsonConverter","href":"Bonsai.ML.HiddenMarkovModels.ModelParametersJsonConverter.html","topicHref":"Bonsai.ML.HiddenMarkovModels.ModelParametersJsonConverter.html","topicUid":"Bonsai.ML.HiddenMarkovModels.ModelParametersJsonConverter"},{"name":"PythonStringBuilder","href":"Bonsai.ML.HiddenMarkovModels.PythonStringBuilder.html","topicHref":"Bonsai.ML.HiddenMarkovModels.PythonStringBuilder.html","topicUid":"Bonsai.ML.HiddenMarkovModels.PythonStringBuilder"},{"name":"SerializeToJson","href":"Bonsai.ML.HiddenMarkovModels.SerializeToJson.html","topicHref":"Bonsai.ML.HiddenMarkovModels.SerializeToJson.html","topicUid":"Bonsai.ML.HiddenMarkovModels.SerializeToJson"},{"name":"StateParameters","href":"Bonsai.ML.HiddenMarkovModels.StateParameters.html","topicHref":"Bonsai.ML.HiddenMarkovModels.StateParameters.html","topicUid":"Bonsai.ML.HiddenMarkovModels.StateParameters"},{"name":"StateParametersJsonConverter","href":"Bonsai.ML.HiddenMarkovModels.StateParametersJsonConverter.html","topicHref":"Bonsai.ML.HiddenMarkovModels.StateParametersJsonConverter.html","topicUid":"Bonsai.ML.HiddenMarkovModels.StateParametersJsonConverter"},{"name":"StateProbability","href":"Bonsai.ML.HiddenMarkovModels.StateProbability.html","topicHref":"Bonsai.ML.HiddenMarkovModels.StateProbability.html","topicUid":"Bonsai.ML.HiddenMarkovModels.StateProbability"}]},{"name":"Bonsai.ML.HiddenMarkovModels.Observations","href":"Bonsai.ML.HiddenMarkovModels.Observations.html","topicHref":"Bonsai.ML.HiddenMarkovModels.Observations.html","topicUid":"Bonsai.ML.HiddenMarkovModels.Observations","items":[{"name":"AutoRegressiveObservations","href":"Bonsai.ML.HiddenMarkovModels.Observations.AutoRegressiveObservations.html","topicHref":"Bonsai.ML.HiddenMarkovModels.Observations.AutoRegressiveObservations.html","topicUid":"Bonsai.ML.HiddenMarkovModels.Observations.AutoRegressiveObservations"},{"name":"AutoRegressiveObservationsModel","href":"Bonsai.ML.HiddenMarkovModels.Observations.AutoRegressiveObservationsModel.html","topicHref":"Bonsai.ML.HiddenMarkovModels.Observations.AutoRegressiveObservationsModel.html","topicUid":"Bonsai.ML.HiddenMarkovModels.Observations.AutoRegressiveObservationsModel"},{"name":"BernoulliObservations","href":"Bonsai.ML.HiddenMarkovModels.Observations.BernoulliObservations.html","topicHref":"Bonsai.ML.HiddenMarkovModels.Observations.BernoulliObservations.html","topicUid":"Bonsai.ML.HiddenMarkovModels.Observations.BernoulliObservations"},{"name":"BernoulliObservationsModel","href":"Bonsai.ML.HiddenMarkovModels.Observations.BernoulliObservationsModel.html","topicHref":"Bonsai.ML.HiddenMarkovModels.Observations.BernoulliObservationsModel.html","topicUid":"Bonsai.ML.HiddenMarkovModels.Observations.BernoulliObservationsModel"},{"name":"CategoricalObservations","href":"Bonsai.ML.HiddenMarkovModels.Observations.CategoricalObservations.html","topicHref":"Bonsai.ML.HiddenMarkovModels.Observations.CategoricalObservations.html","topicUid":"Bonsai.ML.HiddenMarkovModels.Observations.CategoricalObservations"},{"name":"CategoricalObservationsModel","href":"Bonsai.ML.HiddenMarkovModels.Observations.CategoricalObservationsModel.html","topicHref":"Bonsai.ML.HiddenMarkovModels.Observations.CategoricalObservationsModel.html","topicUid":"Bonsai.ML.HiddenMarkovModels.Observations.CategoricalObservationsModel"},{"name":"ExponentialObservations","href":"Bonsai.ML.HiddenMarkovModels.Observations.ExponentialObservations.html","topicHref":"Bonsai.ML.HiddenMarkovModels.Observations.ExponentialObservations.html","topicUid":"Bonsai.ML.HiddenMarkovModels.Observations.ExponentialObservations"},{"name":"ExponentialObservationsModel","href":"Bonsai.ML.HiddenMarkovModels.Observations.ExponentialObservationsModel.html","topicHref":"Bonsai.ML.HiddenMarkovModels.Observations.ExponentialObservationsModel.html","topicUid":"Bonsai.ML.HiddenMarkovModels.Observations.ExponentialObservationsModel"},{"name":"GaussianObservations","href":"Bonsai.ML.HiddenMarkovModels.Observations.GaussianObservations.html","topicHref":"Bonsai.ML.HiddenMarkovModels.Observations.GaussianObservations.html","topicUid":"Bonsai.ML.HiddenMarkovModels.Observations.GaussianObservations"},{"name":"GaussianObservationsModel","href":"Bonsai.ML.HiddenMarkovModels.Observations.GaussianObservationsModel.html","topicHref":"Bonsai.ML.HiddenMarkovModels.Observations.GaussianObservationsModel.html","topicUid":"Bonsai.ML.HiddenMarkovModels.Observations.GaussianObservationsModel"},{"name":"GaussianObservationsStatistics","href":"Bonsai.ML.HiddenMarkovModels.Observations.GaussianObservationsStatistics.html","topicHref":"Bonsai.ML.HiddenMarkovModels.Observations.GaussianObservationsStatistics.html","topicUid":"Bonsai.ML.HiddenMarkovModels.Observations.GaussianObservationsStatistics"},{"name":"GetGaussianObservationsStatisticsFromHMM","href":"Bonsai.ML.HiddenMarkovModels.Observations.GetGaussianObservationsStatisticsFromHMM.html","topicHref":"Bonsai.ML.HiddenMarkovModels.Observations.GetGaussianObservationsStatisticsFromHMM.html","topicUid":"Bonsai.ML.HiddenMarkovModels.Observations.GetGaussianObservationsStatisticsFromHMM"},{"name":"ObservationsLookup","href":"Bonsai.ML.HiddenMarkovModels.Observations.ObservationsLookup.html","topicHref":"Bonsai.ML.HiddenMarkovModels.Observations.ObservationsLookup.html","topicUid":"Bonsai.ML.HiddenMarkovModels.Observations.ObservationsLookup"},{"name":"ObservationsModel","href":"Bonsai.ML.HiddenMarkovModels.Observations.ObservationsModel.html","topicHref":"Bonsai.ML.HiddenMarkovModels.Observations.ObservationsModel.html","topicUid":"Bonsai.ML.HiddenMarkovModels.Observations.ObservationsModel"},{"name":"ObservationsType","href":"Bonsai.ML.HiddenMarkovModels.Observations.ObservationsType.html","topicHref":"Bonsai.ML.HiddenMarkovModels.Observations.ObservationsType.html","topicUid":"Bonsai.ML.HiddenMarkovModels.Observations.ObservationsType"},{"name":"ObservationsTypeJsonConverter","href":"Bonsai.ML.HiddenMarkovModels.Observations.ObservationsTypeJsonConverter.html","topicHref":"Bonsai.ML.HiddenMarkovModels.Observations.ObservationsTypeJsonConverter.html","topicUid":"Bonsai.ML.HiddenMarkovModels.Observations.ObservationsTypeJsonConverter"},{"name":"PoissonObservations","href":"Bonsai.ML.HiddenMarkovModels.Observations.PoissonObservations.html","topicHref":"Bonsai.ML.HiddenMarkovModels.Observations.PoissonObservations.html","topicUid":"Bonsai.ML.HiddenMarkovModels.Observations.PoissonObservations"},{"name":"PoissonObservationsModel","href":"Bonsai.ML.HiddenMarkovModels.Observations.PoissonObservationsModel.html","topicHref":"Bonsai.ML.HiddenMarkovModels.Observations.PoissonObservationsModel.html","topicUid":"Bonsai.ML.HiddenMarkovModels.Observations.PoissonObservationsModel"}]},{"name":"Bonsai.ML.HiddenMarkovModels.Transitions","href":"Bonsai.ML.HiddenMarkovModels.Transitions.html","topicHref":"Bonsai.ML.HiddenMarkovModels.Transitions.html","topicUid":"Bonsai.ML.HiddenMarkovModels.Transitions","items":[{"name":"ConstrainedStationaryTransitions","href":"Bonsai.ML.HiddenMarkovModels.Transitions.ConstrainedStationaryTransitions.html","topicHref":"Bonsai.ML.HiddenMarkovModels.Transitions.ConstrainedStationaryTransitions.html","topicUid":"Bonsai.ML.HiddenMarkovModels.Transitions.ConstrainedStationaryTransitions"},{"name":"ConstrainedStationaryTransitionsModel","href":"Bonsai.ML.HiddenMarkovModels.Transitions.ConstrainedStationaryTransitionsModel.html","topicHref":"Bonsai.ML.HiddenMarkovModels.Transitions.ConstrainedStationaryTransitionsModel.html","topicUid":"Bonsai.ML.HiddenMarkovModels.Transitions.ConstrainedStationaryTransitionsModel"},{"name":"NeuralNetworkRecurrentTransitions","href":"Bonsai.ML.HiddenMarkovModels.Transitions.NeuralNetworkRecurrentTransitions.html","topicHref":"Bonsai.ML.HiddenMarkovModels.Transitions.NeuralNetworkRecurrentTransitions.html","topicUid":"Bonsai.ML.HiddenMarkovModels.Transitions.NeuralNetworkRecurrentTransitions"},{"name":"NeuralNetworkRecurrentTransitionsModel","href":"Bonsai.ML.HiddenMarkovModels.Transitions.NeuralNetworkRecurrentTransitionsModel.html","topicHref":"Bonsai.ML.HiddenMarkovModels.Transitions.NeuralNetworkRecurrentTransitionsModel.html","topicUid":"Bonsai.ML.HiddenMarkovModels.Transitions.NeuralNetworkRecurrentTransitionsModel"},{"name":"StationaryTransitions","href":"Bonsai.ML.HiddenMarkovModels.Transitions.StationaryTransitions.html","topicHref":"Bonsai.ML.HiddenMarkovModels.Transitions.StationaryTransitions.html","topicUid":"Bonsai.ML.HiddenMarkovModels.Transitions.StationaryTransitions"},{"name":"StationaryTransitionsModel","href":"Bonsai.ML.HiddenMarkovModels.Transitions.StationaryTransitionsModel.html","topicHref":"Bonsai.ML.HiddenMarkovModels.Transitions.StationaryTransitionsModel.html","topicUid":"Bonsai.ML.HiddenMarkovModels.Transitions.StationaryTransitionsModel"},{"name":"StickyTransitions","href":"Bonsai.ML.HiddenMarkovModels.Transitions.StickyTransitions.html","topicHref":"Bonsai.ML.HiddenMarkovModels.Transitions.StickyTransitions.html","topicUid":"Bonsai.ML.HiddenMarkovModels.Transitions.StickyTransitions"},{"name":"StickyTransitionsModel","href":"Bonsai.ML.HiddenMarkovModels.Transitions.StickyTransitionsModel.html","topicHref":"Bonsai.ML.HiddenMarkovModels.Transitions.StickyTransitionsModel.html","topicUid":"Bonsai.ML.HiddenMarkovModels.Transitions.StickyTransitionsModel"},{"name":"TransitionsLookup","href":"Bonsai.ML.HiddenMarkovModels.Transitions.TransitionsLookup.html","topicHref":"Bonsai.ML.HiddenMarkovModels.Transitions.TransitionsLookup.html","topicUid":"Bonsai.ML.HiddenMarkovModels.Transitions.TransitionsLookup"},{"name":"TransitionsModel","href":"Bonsai.ML.HiddenMarkovModels.Transitions.TransitionsModel.html","topicHref":"Bonsai.ML.HiddenMarkovModels.Transitions.TransitionsModel.html","topicUid":"Bonsai.ML.HiddenMarkovModels.Transitions.TransitionsModel"},{"name":"TransitionsType","href":"Bonsai.ML.HiddenMarkovModels.Transitions.TransitionsType.html","topicHref":"Bonsai.ML.HiddenMarkovModels.Transitions.TransitionsType.html","topicUid":"Bonsai.ML.HiddenMarkovModels.Transitions.TransitionsType"},{"name":"TransitionsTypeJsonConverter","href":"Bonsai.ML.HiddenMarkovModels.Transitions.TransitionsTypeJsonConverter.html","topicHref":"Bonsai.ML.HiddenMarkovModels.Transitions.TransitionsTypeJsonConverter.html","topicUid":"Bonsai.ML.HiddenMarkovModels.Transitions.TransitionsTypeJsonConverter"}]},{"name":"Bonsai.ML.LinearDynamicalSystems","href":"Bonsai.ML.LinearDynamicalSystems.html","topicHref":"Bonsai.ML.LinearDynamicalSystems.html","topicUid":"Bonsai.ML.LinearDynamicalSystems","items":[{"name":"CreateModelReference","href":"Bonsai.ML.LinearDynamicalSystems.CreateModelReference.html","topicHref":"Bonsai.ML.LinearDynamicalSystems.CreateModelReference.html","topicUid":"Bonsai.ML.LinearDynamicalSystems.CreateModelReference"},{"name":"DeserializeFromJson","href":"Bonsai.ML.LinearDynamicalSystems.DeserializeFromJson.html","topicHref":"Bonsai.ML.LinearDynamicalSystems.DeserializeFromJson.html","topicUid":"Bonsai.ML.LinearDynamicalSystems.DeserializeFromJson"},{"name":"ModelReference","href":"Bonsai.ML.LinearDynamicalSystems.ModelReference.html","topicHref":"Bonsai.ML.LinearDynamicalSystems.ModelReference.html","topicUid":"Bonsai.ML.LinearDynamicalSystems.ModelReference"},{"name":"Reshape","href":"Bonsai.ML.LinearDynamicalSystems.Reshape.html","topicHref":"Bonsai.ML.LinearDynamicalSystems.Reshape.html","topicUid":"Bonsai.ML.LinearDynamicalSystems.Reshape"},{"name":"SerializeToJson","href":"Bonsai.ML.LinearDynamicalSystems.SerializeToJson.html","topicHref":"Bonsai.ML.LinearDynamicalSystems.SerializeToJson.html","topicUid":"Bonsai.ML.LinearDynamicalSystems.SerializeToJson"},{"name":"Slice","href":"Bonsai.ML.LinearDynamicalSystems.Slice.html","topicHref":"Bonsai.ML.LinearDynamicalSystems.Slice.html","topicUid":"Bonsai.ML.LinearDynamicalSystems.Slice"},{"name":"State","href":"Bonsai.ML.LinearDynamicalSystems.State.html","topicHref":"Bonsai.ML.LinearDynamicalSystems.State.html","topicUid":"Bonsai.ML.LinearDynamicalSystems.State"},{"name":"StateComponent","href":"Bonsai.ML.LinearDynamicalSystems.StateComponent.html","topicHref":"Bonsai.ML.LinearDynamicalSystems.StateComponent.html","topicUid":"Bonsai.ML.LinearDynamicalSystems.StateComponent"}]},{"name":"Bonsai.ML.LinearDynamicalSystems.Kinematics","href":"Bonsai.ML.LinearDynamicalSystems.Kinematics.html","topicHref":"Bonsai.ML.LinearDynamicalSystems.Kinematics.html","topicUid":"Bonsai.ML.LinearDynamicalSystems.Kinematics","items":[{"name":"Forecast","href":"Bonsai.ML.LinearDynamicalSystems.Kinematics.Forecast.html","topicHref":"Bonsai.ML.LinearDynamicalSystems.Kinematics.Forecast.html","topicUid":"Bonsai.ML.LinearDynamicalSystems.Kinematics.Forecast"},{"name":"ForecastResult","href":"Bonsai.ML.LinearDynamicalSystems.Kinematics.ForecastResult.html","topicHref":"Bonsai.ML.LinearDynamicalSystems.Kinematics.ForecastResult.html","topicUid":"Bonsai.ML.LinearDynamicalSystems.Kinematics.ForecastResult"},{"name":"KFModelParameters","href":"Bonsai.ML.LinearDynamicalSystems.Kinematics.KFModelParameters.html","topicHref":"Bonsai.ML.LinearDynamicalSystems.Kinematics.KFModelParameters.html","topicUid":"Bonsai.ML.LinearDynamicalSystems.Kinematics.KFModelParameters"},{"name":"KinematicComponent","href":"Bonsai.ML.LinearDynamicalSystems.Kinematics.KinematicComponent.html","topicHref":"Bonsai.ML.LinearDynamicalSystems.Kinematics.KinematicComponent.html","topicUid":"Bonsai.ML.LinearDynamicalSystems.Kinematics.KinematicComponent"},{"name":"KinematicState","href":"Bonsai.ML.LinearDynamicalSystems.Kinematics.KinematicState.html","topicHref":"Bonsai.ML.LinearDynamicalSystems.Kinematics.KinematicState.html","topicUid":"Bonsai.ML.LinearDynamicalSystems.Kinematics.KinematicState"},{"name":"Observation2D","href":"Bonsai.ML.LinearDynamicalSystems.Kinematics.Observation2D.html","topicHref":"Bonsai.ML.LinearDynamicalSystems.Kinematics.Observation2D.html","topicUid":"Bonsai.ML.LinearDynamicalSystems.Kinematics.Observation2D"}]},{"name":"Bonsai.ML.LinearDynamicalSystems.LinearRegression","href":"Bonsai.ML.LinearDynamicalSystems.LinearRegression.html","topicHref":"Bonsai.ML.LinearDynamicalSystems.LinearRegression.html","topicUid":"Bonsai.ML.LinearDynamicalSystems.LinearRegression","items":[{"name":"GridParameters","href":"Bonsai.ML.LinearDynamicalSystems.LinearRegression.GridParameters.html","topicHref":"Bonsai.ML.LinearDynamicalSystems.LinearRegression.GridParameters.html","topicUid":"Bonsai.ML.LinearDynamicalSystems.LinearRegression.GridParameters"},{"name":"KFModelParameters","href":"Bonsai.ML.LinearDynamicalSystems.LinearRegression.KFModelParameters.html","topicHref":"Bonsai.ML.LinearDynamicalSystems.LinearRegression.KFModelParameters.html","topicUid":"Bonsai.ML.LinearDynamicalSystems.LinearRegression.KFModelParameters"},{"name":"MultivariatePDF","href":"Bonsai.ML.LinearDynamicalSystems.LinearRegression.MultivariatePDF.html","topicHref":"Bonsai.ML.LinearDynamicalSystems.LinearRegression.MultivariatePDF.html","topicUid":"Bonsai.ML.LinearDynamicalSystems.LinearRegression.MultivariatePDF"}]},{"name":"Bonsai.ML.Visualizers","href":"Bonsai.ML.Visualizers.html","topicHref":"Bonsai.ML.Visualizers.html","topicUid":"Bonsai.ML.Visualizers","items":[{"name":"BarSeriesOxyPlotBase","href":"Bonsai.ML.Visualizers.BarSeriesOxyPlotBase.html","topicHref":"Bonsai.ML.Visualizers.BarSeriesOxyPlotBase.html","topicUid":"Bonsai.ML.Visualizers.BarSeriesOxyPlotBase"},{"name":"EllipseHelper","href":"Bonsai.ML.Visualizers.EllipseHelper.html","topicHref":"Bonsai.ML.Visualizers.EllipseHelper.html","topicUid":"Bonsai.ML.Visualizers.EllipseHelper"},{"name":"EllipseParameters","href":"Bonsai.ML.Visualizers.EllipseParameters.html","topicHref":"Bonsai.ML.Visualizers.EllipseParameters.html","topicUid":"Bonsai.ML.Visualizers.EllipseParameters"},{"name":"HeatMapSeriesOxyPlotBase","href":"Bonsai.ML.Visualizers.HeatMapSeriesOxyPlotBase.html","topicHref":"Bonsai.ML.Visualizers.HeatMapSeriesOxyPlotBase.html","topicUid":"Bonsai.ML.Visualizers.HeatMapSeriesOxyPlotBase"},{"name":"MultidimensionalArrayVisualizer","href":"Bonsai.ML.Visualizers.MultidimensionalArrayVisualizer.html","topicHref":"Bonsai.ML.Visualizers.MultidimensionalArrayVisualizer.html","topicUid":"Bonsai.ML.Visualizers.MultidimensionalArrayVisualizer"},{"name":"TimeSeriesOxyPlotBase","href":"Bonsai.ML.Visualizers.TimeSeriesOxyPlotBase.html","topicHref":"Bonsai.ML.Visualizers.TimeSeriesOxyPlotBase.html","topicUid":"Bonsai.ML.Visualizers.TimeSeriesOxyPlotBase"}]},{"name":"Bonsai.ML.Visualizers.HiddenMarkovModels","href":"Bonsai.ML.Visualizers.HiddenMarkovModels.html","topicHref":"Bonsai.ML.Visualizers.HiddenMarkovModels.html","topicUid":"Bonsai.ML.Visualizers.HiddenMarkovModels","items":[{"name":"GaussianObservationStatisticsVisualizer","href":"Bonsai.ML.Visualizers.HiddenMarkovModels.GaussianObservationStatisticsVisualizer.html","topicHref":"Bonsai.ML.Visualizers.HiddenMarkovModels.GaussianObservationStatisticsVisualizer.html","topicUid":"Bonsai.ML.Visualizers.HiddenMarkovModels.GaussianObservationStatisticsVisualizer"},{"name":"GaussianObservationsClustersVisualizer","href":"Bonsai.ML.Visualizers.HiddenMarkovModels.GaussianObservationsClustersVisualizer.html","topicHref":"Bonsai.ML.Visualizers.HiddenMarkovModels.GaussianObservationsClustersVisualizer.html","topicUid":"Bonsai.ML.Visualizers.HiddenMarkovModels.GaussianObservationsClustersVisualizer"},{"name":"StateProbabilityVisualizer","href":"Bonsai.ML.Visualizers.HiddenMarkovModels.StateProbabilityVisualizer.html","topicHref":"Bonsai.ML.Visualizers.HiddenMarkovModels.StateProbabilityVisualizer.html","topicUid":"Bonsai.ML.Visualizers.HiddenMarkovModels.StateProbabilityVisualizer"}]},{"name":"Bonsai.ML.Visualizers.LinearDynamicalSystems","href":"Bonsai.ML.Visualizers.LinearDynamicalSystems.html","topicHref":"Bonsai.ML.Visualizers.LinearDynamicalSystems.html","topicUid":"Bonsai.ML.Visualizers.LinearDynamicalSystems","items":[{"name":"ForecastImageOverlay","href":"Bonsai.ML.Visualizers.LinearDynamicalSystems.ForecastImageOverlay.html","topicHref":"Bonsai.ML.Visualizers.LinearDynamicalSystems.ForecastImageOverlay.html","topicUid":"Bonsai.ML.Visualizers.LinearDynamicalSystems.ForecastImageOverlay"},{"name":"ForecastPlotOverlay","href":"Bonsai.ML.Visualizers.LinearDynamicalSystems.ForecastPlotOverlay.html","topicHref":"Bonsai.ML.Visualizers.LinearDynamicalSystems.ForecastPlotOverlay.html","topicUid":"Bonsai.ML.Visualizers.LinearDynamicalSystems.ForecastPlotOverlay"},{"name":"ForecastVisualizer","href":"Bonsai.ML.Visualizers.LinearDynamicalSystems.ForecastVisualizer.html","topicHref":"Bonsai.ML.Visualizers.LinearDynamicalSystems.ForecastVisualizer.html","topicUid":"Bonsai.ML.Visualizers.LinearDynamicalSystems.ForecastVisualizer"},{"name":"KinematicStateVisualizer","href":"Bonsai.ML.Visualizers.LinearDynamicalSystems.KinematicStateVisualizer.html","topicHref":"Bonsai.ML.Visualizers.LinearDynamicalSystems.KinematicStateVisualizer.html","topicUid":"Bonsai.ML.Visualizers.LinearDynamicalSystems.KinematicStateVisualizer"},{"name":"MultivariatePDFVisualizer","href":"Bonsai.ML.Visualizers.LinearDynamicalSystems.MultivariatePDFVisualizer.html","topicHref":"Bonsai.ML.Visualizers.LinearDynamicalSystems.MultivariatePDFVisualizer.html","topicUid":"Bonsai.ML.Visualizers.LinearDynamicalSystems.MultivariatePDFVisualizer"},{"name":"StateComponentVisualizer","href":"Bonsai.ML.Visualizers.LinearDynamicalSystems.StateComponentVisualizer.html","topicHref":"Bonsai.ML.Visualizers.LinearDynamicalSystems.StateComponentVisualizer.html","topicUid":"Bonsai.ML.Visualizers.LinearDynamicalSystems.StateComponentVisualizer"}]}],"memberLayout":"SamePage","pdf":false}
